kii/__init__.py
kii/asyn.py
kii/config.py
kii/syn.py
kii/application/__init__.py
kii/application/aiogrpc.py
kii/application/aiohttps.py
kii/application/grpc.py
kii/application/https.py
kii/domain/__init__.py
kii/domain/aiochannel.py
kii/domain/channel.py
kii/domain/errors/__init__.py
kii/domain/errors/insigth_type.py
kii/domain/errors/payload.py
kii/domain/schemas/__init__.py
kii/domain/schemas/insight.py
kii/domain/schemas/insigth_type.py
kii/domain/schemas/result.py
kii/domain/schemas/payloads/__init__.py
kii/domain/schemas/payloads/event.py
kii/domain/schemas/payloads/ipayload.py
kii/domain/schemas/payloads/log.py
kriptos_kii-0.1.0.dist-info/METADATA
kriptos_kii-0.1.0.dist-info/WHEEL
kriptos_kii-0.1.0.dist-info/top_level.txt
kriptos_kii-0.1.0.dist-info/RECORD
