Metadata-Version: 2.1
Name: kriptos-kii
Version: 0.1.0
Summary: Client for Kriptos Insight Ingestion API
Home-page: https://bitbucket.org/kr-classifier-context/insight-ingestion-client-lib/src
Author: Nelson Garzón
Author-email: ngarzon@kriptos.io
License: UNKNOWN
Project-URL: Bug Tracker, https://kriptosteam.atlassian.net/jira/software/c/projects/KDT/boards/48/backlog?selectedIssue=ISS-316&epics=visible&issueLimit=100&selectedEpic=KDT-73
Platform: UNKNOWN
Classifier: Development Status :: 5 - Production/Stable
Classifier: Programming Language :: Python :: 3.7
Classifier: Operating System :: OS Independent
Requires-Python: >=3.7
Requires-Dist: aiohttp (==3.8.1)
Requires-Dist: requests (==2.27.1)
